Workbook

Sheet ImageTrend Analysis
A1: ImageTrend Inc. - Company Financial Analysis
A3: Historical Revenue Data
A4: Year | B4: Revenue | C4: YoY Growth | D4: Employees | E4: Rev/Employee
A5: 2021 | B5: 10300000 | D5: 180 | E5: =B5/D5
A6: 2022 | B6: 13000000 | C6: =(B6-B5)/B5 | D6: 220 | E6: =B6/D6
A7: 2023 | B7: 17400000 | C7: =(B7-B6)/B6 | D7: 280 | E7: =B7/D7
A8: 2024 | B8: 25200000 | C8: =(B8-B7)/B7 | D8: 345 | E8: =B8/D8
A9: 2025 | B9: 32760000 | C9: =(B9-B8)/B8 | D9: 394 | E9: =B9/D9
A12: Market Position & Customer Base
A13: Total Customers | B13: 3000 | C13: As of 2024
A14: Total Agencies Served | B14: 20000 | C14: EMS, Fire, Hospital
A15: EMS Agencies | B15: 13000 | C15: ePCR Solutions
A16: States Covered | B16: 43 | C16: NEMSIS Compliance
A17: NEMSIS Records Submitted | B17: 356000000 | C17: Cumulative
A18: CSAT Score | B18: 0.974 | C18: 2024 - 3,633 responses
A19: 2024 New Hires | B19: 141 | C19: Growth indicator
A22: Financial Estimates (Private Company)
A23: Estimated 2024 Revenue | B23: 25200000 | C23: GetLatka verified
A24: PE Investment (2023) | B24: 24000000 | C24: Welsh Carson Anderson Stowe
A25: Revenue Multiple (SaaS) | B25: 8 | C25: Industry average 6-10x
A26: Implied Valuation | B26: =B23*B25 | C26: Revenue x Multiple
A27: Estimated EBITDA Margin | B27: 0.2 | C27: SaaS industry avg 15-25%
A28: Estimated EBITDA | B28: =B23*B27
A29: Net Profit Margin Est. | B29: 0.12 | C29: After tax estimate
A30: Estimated Net Profit | B30: =B23*B29

Sheet Revenue Model
A1: Protocol Guide - ImageTrend Distribution Revenue Model
A3: Key Assumptions
A4: ImageTrend Revenue Share | B4: 0.2 | C4: They take 20%
A5: Protocol Guide Revenue Share | B5: 0.8 | C5: You keep 80%
A6: Protocol Guide Monthly Price | B6: 4.99 | C6: Per user/month
A7: Protocol Guide Annual Price | B7: 39 | C7: Per user/year
A8: Annual Discount | B8: =1-(B7/(B6*12)) | C8: Annual vs Monthly
A9: ImageTrend Total EMS Agencies | B9: 13000 | C9: Current customer base
A10: Avg Users per Agency | B10: 25 | C10: Paramedics/EMTs
A11: Total Addressable Users | B11: =B9*B10 | C11: Within ImageTrend
A14: Adoption Scenarios (% of ImageTrend Customer Base)
A15: Scenario | B15: Adoption Rate | C15: Agencies | D15: Users | E15: Monthly Price | F15: Annual Mix | G15: Monthly MRR | H15: ARR | I15: Your 80%
A16: Conservative | B16: 0.02 | C16: =$B$9*B16 | D16: =C16*$B$10 | E16: $B$6 | F16: 0.7 | G16: =D16*((1-F16)*$B$6+F16*$B$7/12) | H16: =G16*12 | I16: =H16*$B$5
A17: Moderate | B17: 0.05 | C17: =$B$9*B17 | D17: =C17*$B$10 | E17: $B$6 | F17: 0.7 | G17: =D17*((1-F17)*$B$6+F17*$B$7/12) | H17: =G17*12 | I17: =H17*$B$5
A18: Optimistic | B18: 0.1 | C18: =$B$9*B18 | D18: =C18*$B$10 | E18: $B$6 | F18: 0.7 | G18: =D18*((1-F18)*$B$6+F18*$B$7/12) | H18: =G18*12 | I18: =H18*$B$5
A19: Aggressive | B19: 0.2 | C19: =$B$9*B19 | D19: =C19*$B$10 | E19: $B$6 | F19: 0.7 | G19: =D19*((1-F19)*$B$6+F19*$B$7/12) | H19: =G19*12 | I19: =H19*$B$5
A22: 5-Year Growth Projection (Moderate Scenario)
A23: Metric | B23: Year 1 | C23: Year 2 | D23: Year 3 | E23: Year 4 | F23: Year 5
A24: Adoption Rate | B24: 0.02 | C24: 0.05 | D24: 0.1 | E24: 0.15 | F24: 0.2
A25: Active Agencies | B25: =$B$9*B24 | C25: =$B$9*C24 | D25: =$B$9*D24 | E25: =$B$9*E24 | F25: =$B$9*F24
A26: Active Users | B26: =B25*$B$10 | C26: =C25*$B$10 | D26: =D25*$B$10 | E26: =E25*$B$10 | F26: =F25*$B$10
A27: Monthly MRR | B27: =B26*((1-0.7)*$B$6+0.7*$B$7/12) | C27: =C26*((1-0.7)*$B$6+0.7*$B$7/12) | D27: =D26*((1-0.7)*$B$6+0.7*$B$7/12) | E27: =E26*((1-0.7)*$B$6+0.7*$B$7/12) | F27: =F26*((1-0.7)*$B$6+0.7*$B$7/12)
A28: Annual ARR | B28: =B27*12 | C28: =C27*12 | D28: =D27*12 | E28: =E27*12 | F28: =F27*12
A29: Your Revenue (80%) | B29: =B28*$B$5 | C29: =C28*$B$5 | D29: =D28*$B$5 | E29: =E28*$B$5 | F29: =F28*$B$5

Sheet Valuation Impact
A1: Protocol Guide - Valuation Impact Analysis
A3: SaaS Valuation Multiples
A4: Growth Rate | B4: ARR Multiple | C4: Notes
A5: <20% | B5: 3-5x | C5: Slow growth SaaS
A6: 20-40% | B6: 5-8x | C6: Moderate growth
A7: 40-60% | B7: 8-12x | C7: High growth
A8: >60% | B8: 12-20x | C8: Hypergrowth
A11: Protocol Guide Valuation Scenarios
A12: Scenario | B12: Your ARR | C12: Multiple | D12: Valuation | E12: Notes
A13: Conservative (2%) | B13: ='Revenue Model'!I16 | C13: 5 | D13: =B13*C13 | E13: Low adoption, modest multiple
A14: Moderate (5%) | B14: ='Revenue Model'!I17 | C14: 8 | D14: =B14*C14 | E14: Reasonable adoption, growth multiple
A15: Optimistic (10%) | B15: ='Revenue Model'!I18 | C15: 10 | D15: =B15*C15 | E15: Strong adoption, premium multiple
A16: Aggressive (20%) | B16: ='Revenue Model'!I19 | C16: 12 | D16: =B16*C16 | E16: Market leader potential
A19: Key Investment Thesis
A20: 1. Distribution through ImageTrend provides access to 13,000+ EMS agencies immediately
A21: 2. No customer acquisition cost - ImageTrend handles sales and marketing
A22: 3. 80% revenue share is strong for a distribution partnership
A23: 4. Recurring revenue model (SaaS) commands premium valuation multiples
A24: 5. Embedded in existing workflow = high retention potential
A25: 6. Path to $1M+ ARR within 2 years at 5% adoption

Sheet Executive Summary
A1: EXECUTIVE SUMMARY
A3: ImageTrend Partnership Opportunity
A4: ImageTrend 2024 Revenue | B4: $25.2M | C4: Verified - GetLatka
A5: ImageTrend Growth Rate | B5: 30%+ | C5: 2023-2024
A6: ImageTrend Estimated Valuation | B6: $150-200M | C6: 6-8x Revenue
A7: ImageTrend EMS Customer Base | B7: 13,000 agencies | C7: Your TAM
A9: Protocol Guide Price | B9: $4.99/mo or $39/yr | C9: Per user
A10: ImageTrend Take Rate | B10: 20% | C10: Distribution fee
A11: Your Revenue Share | B11: 80% | C11: Net to you
A13: Year 1 ARR (Conservative) | B13: ='Revenue Model'!I16 | C13: 2% adoption
A14: Year 1 ARR (Moderate) | B14: ='Revenue Model'!I17 | C14: 5% adoption
A15: Year 3 ARR (Projected) | B15: ='Revenue Model'!F29 | C15: 10% adoption
A16: Year 5 ARR (Projected) | B16: ='Revenue Model'!F29 | C16: 20% adoption
